digital_multimeter/__init__.py
digital_multimeter/cli/__init__.py
digital_multimeter/cli/click.py
digital_multimeter/cli/config.py
digital_multimeter/cli/entrypoints.py
digital_multimeter/exceptions.py
digital_multimeter/main.py
digital_multimeter/multimeters/MultimeterBase.py
digital_multimeter/multimeters/MultimeterEDI9604.py
digital_multimeter/multimeters/MultimeterFortuneFS9721.py
digital_multimeter/multimeters/MultimeterVC870USBHID.py
digital_multimeter/multimeters/__init__.py
digital_multimeter/utils/__init__.py
digital_multimeter/utils/cli_output.py
digital_multimeter-0.5.3.dist-info/LICENSE
digital_multimeter-0.5.3.dist-info/METADATA
digital_multimeter-0.5.3.dist-info/WHEEL
digital_multimeter-0.5.3.dist-info/entry_points.txt
digital_multimeter-0.5.3.dist-info/RECORD
