Metadata-Version: 2.1
Name: digital-multimeter
Version: 0.5.3
Summary: Digital Multimeter provides both a CLI interface and a Python API interface to receive data from a variety of digital multimeters.
License: BSD-2-Clause
Keywords: multimeter,digital multimeter,dmm,Digitech,Digitek,TekPower,UniTrend,Voltcraft
Author: Nicholas de Jong
Author-email: contact@nicholasdejong.com
Requires-Python: >=3.8,<4.0
Classifier: Environment :: Console
Classifier: Intended Audience :: Developers
Classifier: Intended Audience :: Information Technology
Classifier: License :: OSI Approved :: BSD License
Classifier: Programming Language :: Python :: 3
Classifier: Programming Language :: Python :: 3.8
Classifier: Programming Language :: Python :: 3.9
Classifier: Programming Language :: Python :: 3.10
Classifier: Programming Language :: Python :: 3.11
Requires-Dist: click (>=7.0.0,<9.0.0)
Requires-Dist: pyserial (>=3.0.0,<4.0.0)
Requires-Dist: pyusb (>=1.0.0,<2.0.0)
Project-URL: Bug Tracker, https://github.com/ndejong/digital-multimeter/issues
Project-URL: Documentation, https://digital-multimeter.readthedocs.io/en/latest/
Project-URL: Homepage, https://digital-multimeter.readthedocs.io/en/latest/
Project-URL: Repository, https://github.com/ndejong/digital-multimeter.git
